sqllogformatter.py
sqllogformatter-2017.01.1.dist-info/WHEEL
sqllogformatter-2017.01.1.dist-info/METADATA
sqllogformatter-2017.01.1.dist-info/RECORD
